misato/__init__.py
misato/chrome.py
misato/config.py
misato/ffmpeg_processor.py
misato/http_client.py
misato/logger.py
misato/main.py
misato/url_sources.py
misato/utils.py
misato/video_downloader.py
misato-0.8.9.dist-info/licenses/LICENSE
misato-0.8.9.dist-info/METADATA
misato-0.8.9.dist-info/WHEEL
misato-0.8.9.dist-info/entry_points.txt
misato-0.8.9.dist-info/top_level.txt
misato-0.8.9.dist-info/RECORD
