Metadata-Version: 2.4
Name: misato
Version: 0.8.9
Requires-Python: >=3.10
License-File: LICENSE
Requires-Dist: curl_cffi
Requires-Dist: playwright
Requires-Dist: pydantic
Requires-Dist: pydantic_settings
Dynamic: license-file
Dynamic: requires-dist
Dynamic: requires-python
